LICENSE
MANIFEST.in
README.rst
setup.py
piped/__init__.py
piped/conf.py
piped/conf.yml
piped/debugger.py
piped/decorators.py
piped/dependencies.py
piped/evalcontext.py
piped/event.py
piped/exceptions.py
piped/graph.py
piped/log.py
piped/logging.yaml
piped/plugin.py
piped/processing.py
piped/resource.py
piped/scripts.py
piped/service.py
piped/service.tac
piped/util.py
piped/yamlutil.py
piped.egg-info/PKG-INFO
piped.egg-info/SOURCES.txt
piped.egg-info/dependency_links.txt
piped.egg-info/entry_points.txt
piped.egg-info/not-zip-safe
piped.egg-info/requires.txt
piped.egg-info/top_level.txt
piped/plugins/__init__.py
piped/processors/__init__.py
piped/processors/base.py
piped/processors/context_processors.py
piped/processors/datetime_processors.py
piped/processors/file_processors.py
piped/processors/json_processors.py
piped/processors/pipeline_processors.py
piped/processors/process_processors.py
piped/processors/smtp_processors.py
piped/processors/spread_processors.py
piped/processors/tick_processors.py
piped/processors/trace_processors.py
piped/processors/util_processors.py
piped/processors/web_processors.py
piped/processors/xml_processors.py
piped/processors/test/__init__.py
piped/processors/test/test_base.py
piped/processors/test/test_context_processors.py
piped/processors/test/test_datetime_processors.py
piped/processors/test/test_file_processors.py
piped/processors/test/test_json_processors.py
piped/processors/test/test_pipeline_processors.py
piped/processors/test/test_smtp_processors.py
piped/processors/test/test_spread_processors.py
piped/processors/test/test_tick_processors.py
piped/processors/test/test_util_processors.py
piped/processors/test/test_web_processors.py
piped/processors/test/test_xml_processors.py
piped/providers/__init__.py
piped/providers/context_provider.py
piped/providers/pipeline_provider.py
piped/providers/process_provider.py
piped/providers/repl_provider.py
piped/providers/smtp_provider.py
piped/providers/spread_provider.py
piped/providers/stdin_provider.py
piped/providers/system_events_provider.py
piped/providers/tick_provider.py
piped/providers/web_provider.py
piped/providers/test/__init__.py
piped/providers/test/test_context_provider.py
