Metadata-Version: 1.1
Name: piped
Version: 0.5.9
Summary: A framework and application server with pipelines.
Home-page: http://piped.io
Author: Piped Project Contributors
Author-email: piped@librelist.com
License: MIT
Platform: UNKNOWN
Classifier: Development Status :: 4 - Beta
Classifier: License :: OSI Approved :: MIT License
Classifier: Programming Language :: Python :: 2.6
Classifier: Programming Language :: Python :: 2.7
Classifier: Operating System :: OS Independent
Classifier: Framework :: Twisted
Classifier: Topic :: Software Development :: Libraries :: Application Frameworks
